setup.py
nose_sneeze.egg-info/PKG-INFO
nose_sneeze.egg-info/SOURCES.txt
nose_sneeze.egg-info/dependency_links.txt
nose_sneeze.egg-info/entry_points.txt
nose_sneeze.egg-info/requires.txt
nose_sneeze.egg-info/top_level.txt
sneeze/__init__.py
sneeze/nose_interface.py
sneeze/database/__init__.py
sneeze/database/interface.py
sneeze/database/models.py