Metadata-Version: 1.1
Name: nose-sneeze
Version: 0.0.2
Summary: A nose plugin for better reporting
Home-page: http://sneeze.readthedocs.org/
Author: Silas Ray
Author-email: silas.ray@nytimes.com
License: Apache2.0
Platform: UNKNOWN
Classifier: Development Status :: 4 - Beta
Classifier: Intended Audience :: Information Technology
Classifier: Topic :: Software Development :: Quality Assurance
Classifier: Topic :: Software Development :: Testing
